<?xml version="1.0" encoding="UTF-8"?><i><chatserver>chat.bilibili.com</chatserver><chatid>133185656</chatid><mission>0</mission><maxlimit>300</maxlimit><state>0</state><real_name>0</real_name><source>k-v</source><d p="24.59900,5,25,16776960,1641986079,0,e097d417,963808105831112704,10">《 爆 笑 虫 子 》</d><d p="18.62400,5,25,16777215,1637942090,0,972c2e07,58117791443088384,10">肚子抽筋</d><d p="30.00300,1,25,16777215,1630761584,0,2d7088b6,54353138299751936,10">牛顿：“？？？？”</d><d p="13.39600,1,25,16777215,1630424645,0,4806ae50,54176485431871488,10">魔鬼操作看呆我，泡泡舔了又嚼回去</d><d p="5.20200,5,18,8700107,1629372940,0,a1a23f34,53625089317132288,10">我一直以为嘴里是火腿肠。。</d><d p="22.19800,1,25,16707842,1626997593,0,ebefa03f,52352997594234883,10">徐大虾内个笑死我了</d><d p="30.54500,1,25,16707842,1626601983,0,275810ef,52145583941484547,10">技术指导：爆笑虫子</d><d p="13.64600,5,25,15138834,1625839345,0,46c42b40,51745742070480903,10">憨   憨   笑</d><d p="23.67200,5,25,16707842,1621040630,0,33b26d63,49229833603383301,10">尾  气  处  理</d><d p="0.92700,5,25,41194,1620454890,0,5f400f5f,48922737165991943,10">没头脑和不高兴</d><d p="0.05600,5,25,16707842,1619712982,0,2e967657,48533763437101063,10">徐       大       虾    →</d><d p="23.81900,5,25,15138834,1617364059,0,1a604911,47302251232886791,10">肾宝，味道好极了！</d><d p="30.13200,5,25,16777215,1615655319,0,3b5f1a04,46406379320639493,10">爆 笑 虫 子</d><d p="16.75900,5,25,15138834,1614485026,0,f9cc6155,45792809172074501,10">我的嘴嘟起来了</d><d p="11.29800,1,25,16777215,1614274114,0,23ff9d0f,45682230077423619,10">一直以为吃的火腿肠，看了原视频才明白</d><d p="30.88300,1,25,16777215,1614000805,0,cca2f2a5,45538937696944131,10">原来他吃的是口香糖！！！哈哈哈哈哈</d><d p="11.35800,5,25,16777215,1613313639,0,b53923b6,45178664915566595,10">海绵宝宝和派大星</d><d p="16.01300,1,25,15138834,1612084277,0,4a6f8228,44534125069074439,10">1.5太鬼蓄了哈哈哈，嗝(一种语言)</d><d p="25.48000,5,25,16777215,1611545927,0,1c80754c,44251874529378307,10">屁 量 惊 人</d><d p="2.55200,5,25,16707842,1606794406,0,1ff89ef9,41760709287608323,10">海绵宝宝和派大星既视感</d><d p="12.60700,1,25,16777215,1637402675,0,bd14eec4,57834982761297920,9">我一直以为嘴里是爆米花，，</d><d p="13.97800,1,25,16707842,1631372178,0,d11ef33c,54673265600851968,9">派大星，我们一起抓水母吧</d><d p="8.85100,1,25,16777215,1629900617,0,cf7fcd97,53901744076874240,9">捕捉一只野生的二饼八万的粉丝</d><d p="24.06900,1,25,41194,1629778982,0,9d3eecfd,53837972192173056,9">哈哈哈兄弟你上天了</d><d p="19.77800,1,25,38979,1628559277,0,9eb6d5af,53198495506553856,9">徐大虾的笑飞了</d><d p="12.30900,1,25,16777215,1628059963,0,7f60877a,52909985560526851,9">两颗眼球被放到小台子上</d><d p="27.46200,1,25,15138834,1627196698,0,c15457dc,52457386031448071,9">两个憨憨爱跳舞</d><d p="0.73800,5,25,15138834,1626628572,0,c9decc05,52159524499357699,9">你吃泡泡糖的样子▼</d><d p="1.35800,1,25,16707842,1626602012,0,275810ef,52145599143739395,9">技术指导：爆笑虫子</d><d p="30.59900,4,25,6830715,1619365917,0,bd287fdd,48351801424478213,9">笑 死 我 了</d><d p="17.03100,1,25,16777215,1616669783,0,8fd77fc3,46938250898571271,9">我看向了一旁看爆笑虫子的妹妹</d><d p="0.51600,5,25,9033215,1614068654,0,d56649c,45574510218313735,9">逗                               捧</d><d p="23.07700,1,25,16777215,1642411295,0,cccffa7c,967375077544198144,8">《土豆精与茄子精的跨种族交流》</d><d p="24.50800,1,25,8700107,1633753212,0,ed4f57ab,55921612987526656,8">《爆笑虫子真人版》</d><d p="31.16100,1,25,16777215,1628055872,0,e345a660,52907840822575107,8">为什么我也开始笑了起来啊哈哈哈哈哈</d><d p="24.59700,1,25,15772458,1627354627,0,fcd1fcd9,52540186230259719,8">既可爱又沙雕(￣▼￣)</d><d p="0.21800,5,25,15138834,1626628645,0,c9decc05,52159562570006535,8">你吃泡泡糖的样子▲</d><d p="4.36000,1,25,16777215,1620198651,0,471e79fa,48788393896181763,8">小小的樟脑球</d><d p="32.00000,1,25,16777215,1615080125,0,bb428f26,46104812222676997,8">我只有另一半的表情包</d><d p="11.69900,5,25,15138834,1614639323,0,5689cd71,45873705032613891,8">情头出处</d><d p="0.24900,5,25,15138834,1612919128,0,e5b10471,44971827536068611,8">德三                                 苏联</d><d p="0.03800,5,25,15138834,1639462300,0,2ad37a18,58914819628745216,7">打 字 高 手</d><d p="25.65900,5,25,15138834,1639215607,0,8eb798e5,58785481402038272,7">尾  气  处  理</d><d p="15.66600,5,25,16777215,1637230114,0,fea64d8f,57744511253632512,7">手 工 耿</d><d p="1.44900,1,25,16777215,1636111612,0,2817b8ef,57158094254542336,7">派大星和海绵宝宝的日常</d><d p="9.77700,1,25,16777215,1635950390,0,70fbdfef,57073567446303744,7">卧槽！我只想感叹一下，我居然和up的头像一模一样！！！！！</d><d p="16.31100,5,25,15138834,1634982419,0,9a959441,56566071678464512,7">埋下伏笔</d><d p="17.69800,1,25,15138834,1632596205,0,33258960,55315008104149504,7">有些人笑着笑着就没了</d><d p="3.02500,5,25,16777215,1626523490,0,cb174f84,52104431237332999,7">爆笑虫子的灵感来源</d><d p="15.39200,5,25,16765698,1623591974,0,ae28b6e2,50567472704126981,7">郭德纲                                                      于谦</d><d p="8.31600,1,25,16777215,1622866444,0,dbc45df1,50187085745750023,7">小高个好可爱哈哈</d><d p="9.89500,1,25,16777215,1620477164,0,49030979,48934415117058051,7">右边那个真的好像徐大虾啊哈哈哈哈哈哈</d><d p="29.73800,1,25,16777215,1619945043,0,77220d3b,48655430514114567,7">这是一个有昧道的气球</d><d p="29.24800,1,25,16777215,1619878888,0,a47051a9,48620745868705799,7">刚开始讲我以为嚼的口香糖</d><d p="31.20800,1,25,6830715,1616669804,0,8fd77fc3,46938261867200517,7">我看向了爆笑虫子</d><d p="24.43000,5,25,41194,1616629710,0,8f83db5c,46917241231376387,7">于老师验屁</d><d p="1.05900,5,25,15138834,1614639307,0,5689cd71,45873696533905413,7">情头出处</d><d p="11.97900,1,25,16777215,1613208756,0,919d61bf,45123675902443525,7">好沙雕哈哈哈哈哈哈哈</d><d p="17.51700,1,25,16777215,1612690592,0,a9f1183a,44852008552759303,7">又瓦新又可爱的小家伙</d><d p="21.65900,1,25,16777215,1637501889,0,66a6eb55,57886999454747136,6">菊花：我做错了啥</d><d p="14.31700,1,25,16777215,1636989480,0,eb7b33f6,57618349743762944,6">原来他嚼的不是肾宝片儿啊。</d><d p="12.29900,5,25,15138834,1636800516,0,3256e065,57519278007626240,6">万恶之源</d><d p="25.08700,1,25,16777215,1636197773,0,51a00d3c,57203267389338112,6">化学里的尾气收集法！</d><d p="30.59800,1,25,16777215,1634127123,0,6f1035c0,56117650208128000,6">好家伙，人都起飞了。</d><d p="1.86000,5,25,15138834,1633264082,0,46b5f37d,55665168401644032,6">卧龙凤雏</d><d p="24.06600,4,25,16707842,1630392759,0,58ed34f0,54159767796648448,6">尾 气 处 理 笑死我了</d><d p="17.58700,5,25,16646914,1629727879,0,bdacabda,53811179386588672,6">0.5看笑死我了</d><d p="18.73900,1,25,16777215,1620145911,0,3590251e,48760742886768647,6">长沙地铁老放这俩虫子，哈哈哈哈哈啊哈哈哈</d><d p="14.27100,1,25,16777215,1620041843,0,d308997b,48706181150539781,6">我以为我手机响了</d><d p="3.48800,5,25,41194,1619538210,0,72d750a4,48442132528627717,6">郭老师和于老师？</d><d p="23.00500,4,25,16777215,1617874951,0,33dc0623,47570105705955335,6">两头不耽搁</d><d p="18.46200,1,25,16777215,1617463420,0,2df51ef7,47354345376710659,6">表情包可还行</d><d p="17.07600,5,25,16776960,1617198363,0,726cd8eb,47215379103088647,6">我tm正在嚼口香糖</d><d p="7.40400,1,25,16777215,1615599982,0,49e463ad,46377367174119429,6">我以为它嚼的是肠子</d><d p="29.69900,1,25,16777215,1614175284,0,126a2eec,45630415077638149,6">好可爱妈蛋</d><d p="10.57800,1,25,16777215,1613483160,0,ceb321c3,45267542721167363,6">应该和小羊肖恩应该是一个出厂商</d><d p="28.82900,1,25,16777215,1612858532,0,53f9a41c,44940057518276613,6">hhhhh这就是我和姐妹儿些的日常吗hhhhhh</d><d p="1.13800,5,25,16777215,1632317529,0,e39ae423,55168901947833856,5">肾宝片呢？</d><d p="9.97900,1,25,16777215,1631083873,0,2970a00a,54522110579027456,5">这不是我的手机 闹钟铃声吗</d><d p="28.55800,1,25,16777215,1629883352,0,108ea69b,53892692128283648,5">“空中部队”</d><d p="20.11700,1,25,15138834,1617587983,0,eb89b4d9,47419652237164549,5">两个大聪明</d><d p="24.13100,1,25,15138834,1616169522,0,948b3042,46675970235039751,5">bgm就是海绵宝宝里有的</d><d p="29.93800,1,25,16777215,1615696995,0,6d727563,46428229738692615,5">天呐，这放得什么气体</d><d p="5.36700,1,25,16777215,1612083171,0,33ce9168,44533545293578247,5">别搞师虎和于大爷哈哈哈哈哈哈哈哈笑死我了</d><d p="4.93800,1,25,16777215,1625411506,0,f565e37b,51521431456972867,4">每日一遍，防止抑郁</d><d p="1.79800,1,25,16707842,1625029649,0,29b0bc12,51321228113215495,4">就我一人觉得很可爱嘛</d><d p="23.21700,1,25,16777215,1618189367,0,bc4deb48,47734950316736515,4">哈哈哈哈 怎么这么可爱</d><d p="5.39400,1,25,16777215,1617541841,0,dcedb8c6,47395460548657159,4">你看，连虫子都会吹泡泡.成神了</d><d p="18.37000,1,25,16777215,1617443549,0,200ba5c9,47343926848258051,4">救命啊哈哈哈哈哈哈哈哈</d><d p="11.22700,1,25,16777215,1617152676,0,1f7cad9e,47191425864957955,4">表情包出处</d><d p="2.43800,5,25,16646914,1616856872,0,f607a410,47036339427213317,4">小伙子不讲武德</d><d p="4.06600,1,25,16755202,1616313020,0,42df4d73,46751204044701699,4">黄色的好可爱</d><d p="26.83300,4,25,16707842,1609324342,0,b3721a9a,43087124291911685,4">开塞露</d><d p="13.80000,1,25,16777215,1630032314,0,3bca56ad,53970791031227392,3">没头脑和很高兴 </d><d p="22.86500,1,25,16777215,1629397218,0,2d4449d4,53637817977827840,3">哈哈哈哈哈哈神像哈哈哈</d><d p="19.81900,1,25,16777215,1629085701,0,aef31649,53474493073687552,3">还以为我电话响了</d><d p="25.55800,1,25,16777215,1627878421,0,86f13956,52814805331345415,3">这个笑声好像卢卡尔</d><d p="22.37800,1,25,8700107,1627657204,0,748b1728,52698823694745603,3">知道为啥不能把泡泡糖吞肚子里了</d><d p="4.31900,1,25,16777215,1618666947,0,2d3ffd33,47985339970093059,3">hhhh有点可爱</d><d p="22.18400,1,25,16777215,1617516815,0,a1038070,47382339621748739,3">要是这个p爆了那是另一个事了</d><d p="7.09900,1,25,16777215,1613490731,0,923c3a8,45271512221483015,3">没错，是学姐吃蚊子的那一期</d><d p="31.20800,1,25,14811775,1613056867,0,feac3234,45044042278371333,3">祝小彤彤可爱永远⋪(●ൠ●)⋫و牛年快乐✧</d><d p="7.10900,1,25,16777215,1611617119,0,d6e319c,44289199803727877,3">好沙雕哈哈哈哈</d><d p="27.53900,5,25,15138834,1636800535,0,3256e065,57519288283292160,2">哈哈哈哈，</d><d p="15.28800,1,25,16777215,1633424047,0,a04f0ad,55749035941473280,2">而且还刚才吐了个泡泡，还有飞天信号给报了</d><d p="26.33900,5,25,38979,1629800344,0,fe15e00,53849171806499840,2">徐大虾</d><d p="20.83300,5,25,15138834,1627927777,0,c85d53fc,52840681927344131,2">不会锃出痔疮?</d><d p="18.13900,1,25,16777215,1627736509,0,d412d7e5,52740402633506887,2">哇我的表情包啊啊啊</d><d p="17.49800,1,25,16777215,1627194311,0,1f9b99b4,52456134645121027,2">泡泡糖很好吃的亚子</d><d p="2.43800,5,25,16646914,1616856920,0,f607a410,47036364529598467,2">我劝你耗子尾汁</d><d p="3.17900,1,25,16777215,1616249102,0,99ffe603,46717692895821829,2">又在吃肾宝片</d><d p="14.89800,1,25,16777215,1613650464,0,24bc8c76,45355257842106373,2">原来是你！</d><d p="3.51300,5,25,16777215,1613438453,0,5ddee4bb,45244103033618437,2">说阿巴这个梗不好的，很多地方方言就是这样的，了解清楚再来</d><d p="21.55800,1,25,14811775,1613056822,0,feac3234,45044018579505155,2">祝我可爱的闺蜜们，肉肉，小彤彤，海苔新年快乐，万事如意，早日成双成对</d><d p="29.27200,1,25,16777215,1642770973,0,62685af1,970392271467667456,1">再见我的朋友</d><d p="30.49900,1,25,16777215,1642770939,0,62685af1,970391984983097344,1">再见我的朋友</d><d p="23.11800,1,25,16777215,1642751312,0,dd53d679,970227342104952832,1">挖草</d><d p="26.37200,1,25,16777215,1642747350,0,19126c24,970194109043081216,1">啊哈哈哈哈哈哈哈哈哈哈哈哈哈哈哈哈哈哈哈哈哈哈哈哈哈哈哈哈哈哈哈哈哈哈哈哈哈哈哈哈哈哈哈哈哈哈哈哈哈哈哈哈哈哈哈哈哈哈哈哈哈哈</d><d p="17.05900,1,25,16777215,1642741563,0,9fff8050,970145564831096832,1">救命为什么我感觉他的泡泡糖好好吃</d><d p="0.31300,1,25,16777215,1642659354,0,75951474,969455945298862080,1">0.5打开新世界</d><d p="0.21800,1,25,15138834,1642600025,0,85e7069c,968958261673549824,1">右边的好像大虾</d><d p="25.80300,1,25,16777215,1642582786,0,cad92487,968813650252775424,1">五呼呼呼呼</d><d p="29.43600,1,25,16777215,1642568395,0,26ba67ba,968692925279240192,1">气球僵尸</d><d p="13.79800,1,25,16777215,1642391158,0,ca27e9e0,967206150230925312,1">三连</d><d p="26.01900,5,25,16777215,1642321036,0,d9446af9,966617928198684672,1">爷tm在吃饭</d><d p="22.16100,1,25,16777215,1642262827,0,f7def7f5,966129637296283648,1">屁哩屁哩</d><d p="13.33900,1,25,15138834,1639140871,0,90b07c9a,58746298000379904,1">像朱之文的大嘴</d><d p="7.96500,1,25,16777215,1637420687,0,9c1d3333,57844426382592000,1">乌黑！</d><d p="27.17900,1,25,16777215,1636199034,0,da0c24ac,57203928508070912,1">吞泡泡糖就如这个动画一样，会拉出来，就是一种凝胶而已那个华液特别多为力所以会滑下去</d><d p="7.93800,1,25,16777215,1633542720,0,434dc3ce,55811254753387008,1">循环利用</d><d p="9.52800,1,25,16777215,1633424026,0,a04f0ad,55749025003003392,1">这是个什么生物嚼口香糖</d><d p="10.50900,1,25,16707842,1633181924,0,29a9cc3c,55622093756413952,1">这黄的tm长得和我同学一模一样</d><d p="10.83800,1,25,16707842,1632284384,0,bee9dd3d,55151524383019008,1">哒哒哒滴哒～</d><d p="3.47900,5,25,38979,1629800359,0,fe15e00,53849179939256320,1">徐大虾</d><d p="1.14400,1,25,16777215,1628565644,0,fc04d4b0,53201833528881152,1">这是爆笑虫子吧</d><d p="27.59500,1,25,16777215,1624811834,0,5e534299,51207030470868999,1">好鬼畜啊，什么牛马</d><d p="13.61800,1,25,8700107,1623496974,0,4f4678d2,50517664962445319,1">说实话，笑的我肚子疼 </d><d p="2.43800,4,25,16776960,1616857081,0,f607a410,47036448798932995,1">_(:3」∠❀)_菊花碎了一地</d><d p="27.81900,1,25,16777215,1616584862,0,d1a8cf19,46893727573082115,1">♂哲♂学</d><d p="9.34400,1,25,16777215,1613272113,0,5443b137,45156893320019973,1">徐大虾哈哈哈哈</d><d p="1.09800,1,25,14811775,1613056896,0,feac3234,45044057400934403,1">祝小彤彤牛年快乐，永远可爱可爱可爱可爱可爱⋪(●ൠ●)⋫و牛年快乐✧</d><d p="27.57400,1,25,16777215,1612519611,0,fb637102,44762365249978373,1">我在干饭！！！！！</d></i>